neural_network/__init__.py
neural_network/nn/__init__.py
neural_network/nn/core.py
neural_network/utils/__init__.py
neural_network/utils/utillties.py
vic_NeuralNetwork-0.0.2.dist-info/LICENSE
vic_NeuralNetwork-0.0.2.dist-info/METADATA
vic_NeuralNetwork-0.0.2.dist-info/WHEEL
vic_NeuralNetwork-0.0.2.dist-info/top_level.txt
vic_NeuralNetwork-0.0.2.dist-info/RECORD
