Metadata-Version: 2.1
Name: vic-NeuralNetwork
Version: 0.0.2
Summary: This is self-defined neural network framework for self-learning
Home-page: UNKNOWN
Author: Victor
Author-email: 25333456@qq.com
License: UNKNOWN
Platform: UNKNOWN
Classifier: Programming Language :: Python :: 3
Classifier: License :: OSI Approved :: MIT License
Classifier: Operating System :: OS Independent
Requires-Python: >=3.6
